{"cameraMode":{"drawMode":0,"name":"Shaded","section":"Shading Mode"},"sceneLighting":true,"audioPlay":false,"sceneViewState":{"m_AlwaysRefresh":false,"showFog":true,"showSkybox":true,"showFlares":true,"showImageEffects":true,"showParticleSystems":true,"showVisualEffectGraphs":true,"m_FxEnabled":true},"in2DMode":false,"pivot":{"x":-201.49630737304688,"y":-151.8097686767578,"z":318.86395263671877},"rotation":{"x":0.22860835492610932,"y":-0.3029520809650421,"z":0.0750921294093132,"w":0.9221692085266113},"size":169.88670349121095,"orthographic":false}